palindrometool/__init__.py
palindrometool/palindrometool.py
palindrometool-0.1.dist-info/METADATA
palindrometool-0.1.dist-info/WHEEL
palindrometool-0.1.dist-info/top_level.txt
palindrometool-0.1.dist-info/RECORD
