Metadata-Version: 2.1
Name: palindrometool
Version: 0.1
Summary: Check if a word or sentence is a palindrome
Author: Jeet Thakkar
Author-email: thakkarjeet536@gmail.com
Classifier: Programming Language :: Python :: 3
Classifier: Operating System :: OS Independent
Requires-Python: >=3.6
